quecpython_api_stubs/__init__.pyi
quecpython_api_stubs/__main__.py
quecpython_api_stubs/checkNet.pyi
quecpython_api_stubs/gc.pyi
quecpython_api_stubs/math.pyi
quecpython_api_stubs/sys.pyi
quecpython_api_stubs/ubinascii.pyi
quecpython_api_stubs/uio.pyi
quecpython_api_stubs/ujson.pyi
quecpython_api_stubs/uos.pyi
quecpython_api_stubs/urandom.pyi
quecpython_api_stubs/usocket.pyi
quecpython_api_stubs/ustruct.pyi
quecpython_api_stubs/utime.pyi
quecpython_api_stubs-0.0.1.dist-info/METADATA
quecpython_api_stubs-0.0.1.dist-info/WHEEL
quecpython_api_stubs-0.0.1.dist-info/top_level.txt
quecpython_api_stubs-0.0.1.dist-info/RECORD
