Metadata-Version: 2.1
Name: quecpython-api-stubs
Version: 0.0.1
Summary: quecpython_api_stubs for IDE
Home-page: https://github.com/QuecPython/quecpython_api_stubs
Author: dustin.wei
Author-email: dustin.wei@quectel.com
License: MIT License
Keywords: QuecPython,quecpython_api_stubs
Platform: windows
Classifier: Programming Language :: Python :: 3
Classifier: License :: OSI Approved :: MIT License
Classifier: Operating System :: OS Independent
Requires-Python: >=3.7
Requires-Dist: pywin32 (==306)
